WAM_Core-0.4.22.data/data/wamcore/database/abilities_ref.json
WAM_Core-0.4.22.data/data/wamcore/database/characters_ref.json
WAM_Core-0.4.22.data/data/wamcore/database/database.sqlite
WAM_Core-0.4.22.data/data/wamcore/database/experience_table_ref.json
WAM_Core-0.4.22.data/data/wamcore/database/items_ref.json
WAM_Core-0.4.22.data/data/wamcore/database/magic_ref.json
WAM_Core-0.4.22.data/data/wamcore/database/processes_ref.json
WAM_Core-0.4.22.data/data/wamcore/database/warbands_ref.json
wamcore/__init__.py
wamcore/class_components.py
wamcore/class_hierarchy.py
wamcore/methods_database_from.py
wamcore/methods_database_from_copy.py
wamcore/methods_database_to.py
wamcore/methods_engine.py
wamcore/methods_json.py
wamcore/test_json_to_dict.py
wamcore/database/__init__.py
wamcore/database/abilities_ref.json
wamcore/database/abilities_ref.py
wamcore/database/characters_ref.json
wamcore/database/characters_ref.py
wamcore/database/database.sqlite
wamcore/database/database_methods.py
wamcore/database/database_migration.py
wamcore/database/experience_table_ref.json
wamcore/database/experience_table_ref.py
wamcore/database/items_ref.json
wamcore/database/items_ref.py
wamcore/database/magic_ref.json
wamcore/database/magic_ref.py
wamcore/database/processes_ref.json
wamcore/database/processes_ref.py
wamcore/database/warbands_ref.json
wamcore/database/warbands_ref.py
WAM_Core-0.4.22.dist-info/LICENSE
WAM_Core-0.4.22.dist-info/METADATA
WAM_Core-0.4.22.dist-info/WHEEL
WAM_Core-0.4.22.dist-info/top_level.txt
WAM_Core-0.4.22.dist-info/RECORD
