Metadata-Version: 2.1
Name: WAM-Core
Version: 0.4.22
Summary: WAM-Core package
Home-page: https://github.com/Michael-Yongshi/WAM-Core
Author: Michael-Yongshi
Author-email: 4registration@outlook.com
License: UNKNOWN
Platform: UNKNOWN
Classifier: Programming Language :: Python :: 3
Classifier: License :: OSI Approved :: GNU General Public License v3 or later (GPLv3+)
Classifier: Operating System :: OS Independent
Requires-Python: >=3.5
